firfol/__init__.py
firfol/allfuncs.py
firfol/firstfollow.py
firfol-0.2.1.dist-info/METADATA
firfol-0.2.1.dist-info/WHEEL
firfol-0.2.1.dist-info/top_level.txt
firfol-0.2.1.dist-info/RECORD
